[
  {"id": "G1", "name": "Nafsu makan menurun", "description": "Ikan tidak mau makan atau makan sangat sedikit", "species": ["Lele", "Nila", "Gurame"]},
  {"id": "G2", "name": "Ikan berenang tidak normal atau megap-megap di permukaan", "description": "Ikan kesulitan bernapas", "species": ["Lele", "Nila", "Gurame"]},
  {"id": "G3", "name": "Bintik putih pada kulit atau sirip", "description": "Terlihat bintik putih kecil", "species": ["Lele", "Nila", "Gurame"]},
  {"id": "G4", "name": "Luka atau borok pada tubuh ikan", "description": "Luka terbuka pada kulit", "species": ["Lele", "Nila", "Gurame"]},
  {"id": "G5", "name": "Insang pucat atau rusak", "description": "Insang berubah warna atau rusak", "species": ["Lele", "Nila", "Gurame"]},
  {"id": "G6", "name": "Tubuh ikan berlendir berlebih", "description": "Produksi lendir berlebihan", "species": ["Lele", "Nila", "Gurame"]},
  {"id": "G7", "name": "Sirip rusak atau terkikis", "description": "Sirip robek atau terkikis", "species": ["Lele", "Nila", "Gurame"]},
  {"id": "G8", "name": "Warna tubuh memucat", "description": "Warna ikan menjadi pucat", "species": ["Lele", "Nila", "Gurame"]},
  {"id": "G9", "name": "Ikan sering menggosokkan tubuh ke dasar kolam", "description": "Perilaku menggosok tubuh", "species": ["Lele", "Nila", "Gurame"]},
  {"id": "G10", "name": "Ikan lemas dan cenderung diam di dasar", "description": "Ikan tidak aktif", "species": ["Lele", "Nila", "Gurame"]},
  {"id": "G11", "name": "Terdapat kutu air menempel pada tubuh ikan", "description": "Parasit terlihat menempel", "species": ["Lele", "Nila", "Gurame"]},
  {"id": "G12", "name": "Mata ikan menonjol atau bengkak", "description": "Mata membesar abnormal", "species": ["Lele", "Nila", "Gurame"]},
  {"id": "G13", "name": "Terdapat perdarahan pada sirip atau tubuh ikan", "description": "Pendarahan terlihat jelas", "species": ["Lele", "Nila", "Gurame"]},
  {"id": "G14", "name": "Permukaan tubuh tampak kasar atau kusam", "description": "Tekstur kulit berubah", "species": ["Lele", "Nila", "Gurame"]},
  {"id": "G15", "name": "Perut kembung atau bengkak (dropsy)", "description": "Perut membesar abnormal", "species": ["Lele", "Nila", "Gurame"]},
  {"id": "G16", "name": "Tumbuh lapisan seperti kapas putih/abu-abu pada tubuh atau luka", "description": "Infeksi jamur terlihat", "species": ["Lele", "Nila", "Gurame"]},
  {"id": "G17", "name": "Sisik terlepas atau mengelupas (scale protrusion)", "description": "Sisik rontok", "species": ["Lele", "Nila", "Gurame"]},
  {"id": "G18", "name": "Pendarahan spesifik di pangkal sirip atau sekitar mulut", "description": "Pendarahan pada area tertentu", "species": ["Lele", "Nila", "Gurame"]},
  {"id": "G19", "name": "Air kolam keruh, berbau busuk, atau berbusa", "description": "Kualitas air buruk", "species": ["Lele", "Nila", "Gurame"]}
]